LICENSE.txt
README.md
setup.cfg
setup.py
Topsis_101917193_Vidushi/__init__.py
Topsis_101917193_Vidushi/topsis.py
Topsis_Vidushi_101917193.egg-info/PKG-INFO
Topsis_Vidushi_101917193.egg-info/SOURCES.txt
Topsis_Vidushi_101917193.egg-info/dependency_links.txt
Topsis_Vidushi_101917193.egg-info/requires.txt
Topsis_Vidushi_101917193.egg-info/top_level.txt