Metadata-Version: 2.1
Name: Topsis-Vidushi-101917193
Version: 0.1
Summary: A python package to implement topsis
Home-page: UNKNOWN
Author: Vidushi Goyal
Author-email: goyalvidushi2@gmail.com
License: MIT
Keywords: topsis,Rank,Best,Model
Platform: UNKNOWN
Classifier: Programming Language :: Python :: 3
Classifier: License :: OSI Approved :: MIT License
Classifier: Operating System :: OS Independent
License-File: LICENSE.txt
